{"name": "Galactic and extragalactic astronomy (214)", "children": [{"name": "Astrophysical masers (4)", "children": [{"name": "Hydroxyl masers (0)"}, {"name": "Megamasers (0)"}, {"name": "Silicon monoxide masers (0)"}, {"name": "Water masers (0)"}]}, {"name": "Extragalactic magnetic fields (0)"}, {"name": "Galactic accretion disks (0)"}, {"name": "Galactic physics (50)", "children": [{"name": "Galactic processes (7)", "children": [{"name": "Galactic accretion (1)", "children": [{"name": "Galactic infall (0)"}]}, {"name": "Galactic dynamics (0)"}, {"name": "Galactic evolution (0)"}, {"name": "Galactic fountains (0)"}, {"name": "Galactic kinematics (0)"}, {"name": "Galactic winds (0)"}]}, {"name": "Galactic properties (15)", "children": [{"name": "Galactic ages (0)"}, {"name": "Galactic chemical composition (0)"}, {"name": "Galactic colors (0)"}, {"name": "Galactic electric fields (0)"}, {"name": "Galactic fountains (0)"}, {"name": "Galactic jets (0)"}, {"name": "Galactic luminosities (0)"}, {"name": "Galactic magnetic fields (0)"}, {"name": "Galactic magnitudes (0)"}, {"name": "Galactic masses (2)", "children": [{"name": "Galactic mass distribution (1)", "children": [{"name": "Navarro-Frenk-White profile (0)"}]}]}, {"name": "Galactic radial velocities (0)"}, {"name": "Galactic radii (0)"}, {"name": "Galactic stellar content (0)"}]}, {"name": "Galactic spurs (0)"}, {"name": "Galactic structure (3)", "children": [{"name": "Galactic halo (0)"}, {"name": "Galactic pitch angle (0)"}, {"name": "Radio cores (0)"}]}, {"name": "Galaxy abundances (0)"}, {"name": "Galaxy distances (2)", "children": [{"name": "Holmberg radius (0)"}, {"name": "Hubble radius (0)"}]}, {"name": "Galaxy distribution (2)", "children": [{"name": "Galaxy cluster counts (0)"}, {"name": "Galaxy voids (0)"}]}, {"name": "Galaxy dynamics (0)"}, {"name": "Galaxy encounters (0)"}, {"name": "Galaxy formation (2)", "children": [{"name": "Density wave model (0)"}, {"name": "Stellar feedback (0)"}]}, {"name": "Galaxy interactions (1)", "children": [{"name": "Galaxy mergers (0)"}]}, {"name": "Galaxy kinematics (6)", "children": [{"name": "Galactic anticenters (0)"}, {"name": "Galactic equators (0)"}, {"name": "Galactic planes (0)"}, {"name": "Galactic rotation (2)", "children": [{"name": "Galaxy rotation curves (0)"}, {"name": "Oort formulae (0)"}]}]}]}, {"name": "Galaxies (116)", "children": [{"name": "Active galaxies (25)", "children": [{"name": "Active galactic nuclei (9)", "children": [{"name": "Blazars (0)"}, {"name": "Quasars (7)", "children": [{"name": "Broad-absorption line quasar (0)"}, {"name": "Double quasars (0)"}, {"name": "Individual quasars (0)"}, {"name": "Quasar-galaxy pairs (0)"}, {"name": "Radio loud quasars (0)"}, {"name": "Radio quiet quasars (0)"}, {"name": "X-ray quasars (0)"}]}]}, {"name": "BL Lacertae objects (0)"}, {"name": "Blazars (0)"}, {"name": "Haro galaxies (0)"}, {"name": "LINER galaxies (0)"}, {"name": "Markarian galaxies (0)"}, {"name": "Radio galaxies (4)", "children": [{"name": "Fanaroff-Riley radio galaxies (0)"}, {"name": "Giant radio galaxies (0)"}, {"name": "Peculiar elliptical galaxies (0)"}, {"name": "Tailed radio galaxies (0)"}]}, {"name": "Starburst galaxies (4)", "children": [{"name": "Infrared galaxies (3)", "children": [{"name": "IRAS galaxies (0)"}, {"name": "Luminous infrared galaxies (0)"}, {"name": "Ultraluminous infrared galaxies (0)"}]}]}]}, {"name": "Blue galaxies (0)"}, {"name": "Bright galaxies (0)"}, {"name": "Compact galaxies (1)", "children": [{"name": "N galaxies (0)"}]}, {"name": "Companion galaxies (0)"}, {"name": "Disk galaxies (8)", "children": [{"name": "Hypergalaxies (0)"}, {"name": "Lenticular galaxies (0)"}, {"name": "Ring galaxies (0)"}, {"name": "Spiral galaxies (4)", "children": [{"name": "Andromeda Galaxy (0)"}, {"name": "Barred spiral galaxies (0)"}, {"name": "Triangulum Galaxy (0)"}, {"name": "Unbarred spiral galaxies (0)"}]}]}, {"name": "Dwarf galaxies (4)", "children": [{"name": "Dwarf elliptical galaxies (0)"}, {"name": "Dwarf irregular galaxies (0)"}, {"name": "Dwarf spheroidal galaxies (0)"}, {"name": "Ultracompact dwarf galaxies (0)"}]}, {"name": "Early-type galaxies (0)"}, {"name": "Elliptical galaxies (5)", "children": [{"name": "D galaxies (1)", "children": [{"name": "cD galaxies (0)"}]}, {"name": "E galaxies (1)", "children": [{"name": "Peculiar elliptical galaxies (0)"}]}, {"name": "Giant elliptical galaxies (0)"}]}, {"name": "Emission line galaxies (3)", "children": [{"name": "LINER galaxies (0)"}, {"name": "Markarian galaxies (0)"}, {"name": "Seyfert galaxies (0)"}]}, {"name": "Faint galaxies (0)"}, {"name": "Field galaxies (0)"}, {"name": "Galaxy components (21)", "children": [{"name": "Galactic bulges (0)"}, {"name": "Galactic circumnuclear matter (0)"}, {"name": "Galactic disks (2)", "children": [{"name": "Gaseous disks (0)"}, {"name": "Stellar disks (0)"}]}, {"name": "Galactic halos (1)", "children": [{"name": "Stellar rings (0)"}]}, {"name": "Galactic nuclei (11)", "children": [{"name": "Active galactic nuclei (9)", "children": [{"name": "Blazars (0)"}, {"name": "Quasars (7)", "children": [{"name": "Broad-absorption line quasar (0)"}, {"name": "Double quasars (0)"}, {"name": "Individual quasars (0)"}, {"name": "Quasar-galaxy pairs (0)"}, {"name": "Radio loud quasars (0)"}, {"name": "Radio quiet quasars (0)"}, {"name": "X-ray quasars (0)"}]}]}, {"name": "Compact nuclei (0)"}]}, {"name": "Spiral arms (0)"}, {"name": "Tidal tails (0)"}]}, {"name": "Giant galaxies (2)", "children": [{"name": "Giant elliptical galaxies (0)"}, {"name": "cD galaxies (0)"}]}, {"name": "High-redshift galaxies (0)"}, {"name": "Infrared excess galaxies (0)"}, {"name": "Interacting galaxies (5)", "children": [{"name": "Galactic tides (0)"}, {"name": "Galaxy collisions (0)"}, {"name": "Galaxy mergers (0)"}, {"name": "Galaxy pairs (0)"}, {"name": "Galaxy triplets (0)"}]}, {"name": "Irregular galaxies (5)", "children": [{"name": "I galaxies (0)"}, {"name": "Magellanic Clouds (3)", "children": [{"name": "Large Magellanic Cloud (0)"}, {"name": "Magellanic Stream (0)"}, {"name": "Small Magellanic Cloud (0)"}]}]}, {"name": "L galaxies (0)"}, {"name": "Late-type galaxies (0)"}, {"name": "Massive galaxies (1)", "children": [{"name": "cD galaxies (0)"}]}, {"name": "Multiple galaxies (1)", "children": [{"name": "Double galaxies (0)"}]}, {"name": "Nearby galaxies (0)"}, {"name": "Peculiar galaxies (0)"}, {"name": "Primordial galaxies (0)"}, {"name": "Protogalaxies (0)"}, {"name": "Quasar-galaxy pairs (0)"}, {"name": "Radio jets (2)", "children": [{"name": "Polar jets (0)"}, {"name": "Relativistic jets (0)"}]}, {"name": "Starburst galaxies (4)", "children": [{"name": "Infrared galaxies (3)", "children": [{"name": "IRAS galaxies (0)"}, {"name": "Luminous infrared galaxies (0)"}, {"name": "Ultraluminous infrared galaxies (0)"}]}]}]}, {"name": "Galaxy clusters (6)", "children": [{"name": "Abell clusters (0)"}, {"name": "Coma Cluster (0)"}, {"name": "Intracluster medium (0)"}, {"name": "Superclusters (1)", "children": [{"name": "Virgo Supercluster (0)"}]}, {"name": "Virgo Cluster (0)"}]}, {"name": "Galaxy groups (20)", "children": [{"name": "Hickson compact group (0)"}, {"name": "Local Group (18)", "children": [{"name": "Andromeda Galaxy (0)"}, {"name": "Magellanic Clouds (3)", "children": [{"name": "Large Magellanic Cloud (0)"}, {"name": "Magellanic Stream (0)"}, {"name": "Small Magellanic Cloud (0)"}]}, {"name": "Milky Way Galaxy (11)", "children": [{"name": "Galactic Center (0)"}, {"name": "Gould Belt (0)"}, {"name": "Milky Way disk (0)"}, {"name": "Milky Way dynamics (0)"}, {"name": "Milky Way evolution (0)"}, {"name": "Milky Way formation (0)"}, {"name": "Milky Way galactic halo (0)"}, {"name": "Milky Way magnetic fields (0)"}, {"name": "Milky Way mass (0)"}, {"name": "Milky Way rotation (0)"}, {"name": "Solar neighborhood (0)"}]}, {"name": "Triangulum Galaxy (0)"}]}]}, {"name": "Intergalactic medium (10)", "children": [{"name": "Dark matter (4)", "children": [{"name": "Baryonic dark matter (0)"}, {"name": "Cold dark matter (0)"}, {"name": "Hot dark matter (0)"}, {"name": "Warm dark matter (0)"}]}, {"name": "Intergalactic clouds (1)", "children": [{"name": "Intergalactic dust clouds (0)"}]}, {"name": "Intergalactic gas (0)"}, {"name": "Missing mass (0)"}, {"name": "Warm-hot intergalactic medium (0)"}]}]}